lightmlboard/__init__.py
lightmlboard/appml.py
lightmlboard/competition.py
lightmlboard/dbengine.py
lightmlboard/dbmanager.py
lightmlboard/default_options.py
lightmlboard/handlersml.py
lightmlboard/options_helpers.py
lightmlboard/data/__init__.py
lightmlboard/metrics/__init__.py
lightmlboard/metrics/classification.py
lightmlboard/metrics/regression.py
lightmlboard/metrics/regression_custom.py
lightmlboard/static/__init__.py
lightmlboard/static/giphy.gif
lightmlboard/static/icon.ico
lightmlboard/static/icon.png
lightmlboard/static/style.css
lightmlboard/static/style_sphinx.css
lightmlboard/templates/__init__.py
lightmlboard/templates/challenge.fr.html
lightmlboard/templates/index.fr.html
lightmlboard/templates/login.fr.html
lightmlboard/templates/submit.fr.html
lightmlboard/templates/waiting.fr.html
lightmlboard-0.1.26.dist-info/DESCRIPTION.rst
lightmlboard-0.1.26.dist-info/METADATA
lightmlboard-0.1.26.dist-info/RECORD
lightmlboard-0.1.26.dist-info/WHEEL
lightmlboard-0.1.26.dist-info/metadata.json
lightmlboard-0.1.26.dist-info/top_level.txt
