Metadata-Version: 2.0
Name: lightmlboard
Version: 0.1.26
Summary: Light web server serving pages on a leaderboard for machine learned competitions
Home-page: http://www.xavierdupre.fr/app/lightmlboard/helpsphinx/index.html
Author: Xavier Dupré
Author-email: xavier.dupre@gmail.com
License: MIT
Download-URL: https://github.com/sdpython/lightmlboard/
Keywords: lightmlboard,Xavier Dupré
Platform: UNKNOWN
Classifier: Programming Language :: Python :: 3
Classifier: Intended Audience :: Developers
Classifier: Topic :: Scientific/Engineering
Classifier: Topic :: Education
Classifier: License :: OSI Approved :: MIT License
Classifier: Development Status :: 5 - Production/Stable
Requires-Dist: numpy
Requires-Dist: pandas
Requires-Dist: tornado
